pandas_ti/__init__.py
pandas_ti/accessor_dataframe.py
pandas_ti/accessor_series.py
pandas_ti/registry.py
pandas_ti/indicators_dataframe/ARTR.py
pandas_ti/indicators_dataframe/ATR.py
pandas_ti/indicators_dataframe/RTR.py
pandas_ti/indicators_dataframe/SRTR.py
pandas_ti/indicators_dataframe/TR.py
pandas_ti/indicators_dataframe/ZigZag.py
pandas_ti/indicators_dataframe/__init__.py
pandas_ti/indicators_series/EMA.py
pandas_ti/indicators_series/SMA.py
pandas_ti/indicators_series/__init__.py
pandas_ti-1.1.0.dist-info/METADATA
pandas_ti-1.1.0.dist-info/WHEEL
pandas_ti-1.1.0.dist-info/licenses/LICENSE
pandas_ti-1.1.0.dist-info/RECORD
