Metadata-Version: 2.4
Name: pandas_ti
Version: 1.1.0
Summary: A lightweight technical indicators library for pandas DataFrames and Series
Author: Javier Calzada Espuny
License: MIT
License-File: LICENSE
Keywords: finance,pandas,technical-indicators,trading
Requires-Python: >=3.12
Requires-Dist: numpy>=2.3.3
Requires-Dist: pandas>=2.3.3
Requires-Dist: rich>=14.2.0
Requires-Dist: scipy>=1.16.2
Requires-Dist: statsmodels>=0.14.5
Provides-Extra: dev
Requires-Dist: ipykernel>=7.0.1; extra == 'dev'
Requires-Dist: ipython>=9.6.0; extra == 'dev'
Requires-Dist: jupyterlab>=4.4.9; extra == 'dev'
Requires-Dist: matplotlib>=3.10.7; extra == 'dev'
Requires-Dist: mplfinance>=0.12.10b0; extra == 'dev'
Requires-Dist: notebook>=7.4.7; extra == 'dev'
Requires-Dist: yfinance>=0.2.66; extra == 'dev'
